modulo_vki/__init__.py
modulo_vki/modulo.py
modulo_vki/modulo_old.py
modulo_vki/core/__init__.py
modulo_vki/core/_dft.py
modulo_vki/core/_dmd_s.py
modulo_vki/core/_k_matrix.py
modulo_vki/core/_mpod_space.py
modulo_vki/core/_mpod_time.py
modulo_vki/core/_pod_space.py
modulo_vki/core/_pod_time.py
modulo_vki/core/_spod_s.py
modulo_vki/core/_spod_t.py
modulo_vki/core/spatial_structures.py
modulo_vki/core/temporal_structures.py
modulo_vki/core/utils.py
modulo_vki/utils/__init__.py
modulo_vki/utils/_plots.py
modulo_vki/utils/_utils.py
modulo_vki/utils/others.py
modulo_vki/utils/read_db.py
modulo_vki-2.1.4.dist-info/licenses/LICENSE
modulo_vki_2/__init__.py
modulo_vki_2/modulo.py
modulo_vki_2/utils.py
modulo_vki-2.1.4.dist-info/METADATA
modulo_vki-2.1.4.dist-info/WHEEL
modulo_vki-2.1.4.dist-info/top_level.txt
modulo_vki-2.1.4.dist-info/RECORD
