Metadata-Version: 2.4
Name: modulo_vki
Version: 2.1.4
Summary: MODULO (MODal mULtiscale pOd) is a software developed at the von Karman Institute to perform Multiscale Modal Analysis of numerical and experimental data.
Home-page: https://github.com/mendezVKI/MODULO/tree/master/modulo_python_package/
Author: ['R. Poletti', 'L. Schena', 'D. Ninni', 'M. A. Mendez']
Author-email: mendez@vki.ac.be
License: BSD (3-clause)
Classifier: Development Status :: 4 - Beta
Classifier: Natural Language :: English
Classifier: Programming Language :: Python :: 3
Requires-Python: >=3.6
License-File: LICENSE
Requires-Dist: tqdm
Requires-Dist: numpy
Requires-Dist: scipy
Requires-Dist: scikit-learn
Requires-Dist: ipykernel
Requires-Dist: ipython
Requires-Dist: ipython-genutils
Requires-Dist: ipywidgets
Requires-Dist: matplotlib
Dynamic: author
Dynamic: author-email
Dynamic: classifier
Dynamic: description
Dynamic: description-content-type
Dynamic: home-page
Dynamic: license
Dynamic: license-file
Dynamic: requires-dist
Dynamic: requires-python
Dynamic: summary
